{
	"name": "esaenz7azds201",
	"properties": {
		"linkedServiceName": {
			"referenceName": "AzureDataLakeStorage1",
			"type": "LinkedServiceReference"
		},
		"parameters": {
			"filename": {
				"type": "string",
				"defaultValue": "data2.csv"
			},
			"path": {
				"type": "String",
				"defaultValue": "silver"
			}
		},
		"annotations": [],
		"type": "DelimitedText",
		"typeProperties": {
			"location": {
				"type": "AzureBlobFSLocation",
				"fileName": "@dataset().filename",
				"folderPath": "@dataset().path",
				"fileSystem": "esaenzazdl101"
			},
			"columnDelimiter": ",",
			"escapeChar": "\\",
			"firstRowAsHeader": true,
			"quoteChar": "\""
		},
		"schema": [
			{
				"name": "EventId",
				"type": "String"
			},
			{
				"name": "Type",
				"type": "String"
			},
			{
				"name": "Severity",
				"type": "String"
			},
			{
				"name": "StartTime(UTC)",
				"type": "String"
			},
			{
				"name": "EndTime(UTC)",
				"type": "String"
			},
			{
				"name": "TimeZone",
				"type": "String"
			},
			{
				"name": "AirportCode",
				"type": "String"
			},
			{
				"name": "LocationLat",
				"type": "String"
			},
			{
				"name": "LocationLng",
				"type": "String"
			},
			{
				"name": "City",
				"type": "String"
			},
			{
				"name": "County",
				"type": "String"
			},
			{
				"name": "State",
				"type": "String"
			},
			{
				"name": "ZipCode",
				"type": "String"
			}
		]
	}
}